{
  "key": "mnp-16-8-ADB-DTP",
  "name": "WK8 ADB @ DTP",
  "type": "manual",
  "week": "8",
  "round": 4,
  "create_at": 1667779613754,
  "date": "11/07/2022",
  "state": "complete",
  "venue": {
    "key": "JUP",
    "name": "Jupiter",
    "machines": [
      "Sopranos",
      "Godzilla",
      "NGG",
      "RollerGames",
      "Star Trek (Bally)",
      "StrangerThings",
      "WCS",
      "POTC",
      "BKSoR",
      "SternPark",
      "SternTrek",
      "BSD",
      "IronMaiden",
      "Getaway",
      "Harlem",
      "TZ",
      "AFM",
      "GOT",
      "SpaceInvaders",
      "TAF",
      "FT",
      "MM",
      "TWD",
      "Paragon",
      "MB",
      "Metallica",
      "Hotdoggin'",
      "Future Spa",
      "Embryon",
      "ACDC"
    ]
  },
  "away": {
    "name": "Admiraballs",
    "key": "ADB",
    "captains": [
      {
        "key": "f69f2cc7fc9237f2685addaa14a2ae2ec8709451",
        "name": "Scott Helgason"
      },
      {
        "key": "cb2459e80c52fefe189d0b6a3dbca979c0f09ddd",
        "name": "Maria Reidell"
      }
    ],
    "lineup": [
      {
        "key": "1bf098b4ddbff230efd9c925eca3322cd8461f85",
        "name": "Casey Garcia",
        "sub": false,
        "num_played": 3,
        "IPR": 1
      },
      {
        "key": "666ef16d5cfc2ae722bd45643157f3c13eae0062",
        "name": "Chris Borgstadt",
        "sub": false,
        "num_played": 3,
        "IPR": 6
      },
      {
        "key": "f9bd75da89cd62f8e95d7e0a37685da3810c8183",
        "name": "Denton Dickson",
        "sub": false,
        "num_played": 3,
        "IPR": 2
      },
      {
        "key": "a0a68005f40b140a03290f64bb8cd03353f48c1e",
        "name": "Jackson McComish",
        "sub": false,
        "num_played": 3,
        "IPR": 4
      },
      {
        "key": "d2f7345141f115afae0cd9ea551018a8a7d12528",
        "name": "Kiko Correa",
        "sub": false,
        "num_played": 3,
        "IPR": 1
      },
      {
        "key": "cb2459e80c52fefe189d0b6a3dbca979c0f09ddd",
        "name": "Maria Reidell",
        "sub": false,
        "num_played": 3,
        "IPR": 1
      },
      {
        "key": "a693ae0dd694c79f9af8ce9b9a3e612c8a61a4b8",
        "name": "Matthew Greene",
        "sub": false,
        "num_played": 3,
        "IPR": 3
      },
      {
        "key": "a9c6b74c710fe3b6ba45629b220c148a2003f162",
        "name": "Michael Tomber",
        "sub": false,
        "num_played": 3,
        "IPR": 3
      },
      {
        "key": "2f42b169d65f318007e360e5fa8e414764304e25",
        "name": "Ryan Eakes",
        "sub": false,
        "num_played": 3,
        "IPR": 1
      },
      {
        "key": "f69f2cc7fc9237f2685addaa14a2ae2ec8709451",
        "name": "Scott Helgason",
        "sub": false,
        "num_played": 3,
        "IPR": 5
      }
    ],
    "ready": true,
    "confirmed": {
      "by": "Dwayne Collins",
      "at": 1667881995468
    }
  },
  "home": {
    "name": "DTP",
    "key": "DTP",
    "captains": [
      {
        "key": "3f1d455e7fd930d2509ad908e2231f4f2ace791e",
        "name": "Dwayne Collins"
      },
      {
        "key": "e6b671979862b1ede4ab48b617b4ede86bba27bc",
        "name": "Jamie Winsor"
      }
    ],
    "lineup": [
      {
        "key": "04fda437f422f17681c39fae5ba7d3a8e4a3282f",
        "name": "Alex Hawley",
        "sub": false,
        "num_played": 3,
        "IPR": 2
      },
      {
        "key": "b4c6f4a0222bf84e9811cf283febf386684852d5",
        "name": "Alex Skinner",
        "sub": false,
        "num_played": 3,
        "IPR": 5
      },
      {
        "key": "3f1d455e7fd930d2509ad908e2231f4f2ace791e",
        "name": "Dwayne Collins",
        "sub": false,
        "num_played": 3,
        "IPR": 2
      },
      {
        "key": "e6b671979862b1ede4ab48b617b4ede86bba27bc",
        "name": "Jamie Winsor",
        "sub": false,
        "num_played": 3,
        "IPR": 5
      },
      {
        "key": "a5863561101172aa1631bd35d0911b8bd136b117",
        "name": "Kevin Coffey",
        "sub": false,
        "num_played": 3,
        "IPR": 5
      },
      {
        "key": "e10076f402847f4055455fc4d2717fc3ae14078e",
        "name": "Kristin Vick",
        "sub": false,
        "num_played": 3,
        "IPR": 3
      },
      {
        "key": "db6c5cd060abb9e3a5da8370c2c3e9c0ef198a45",
        "name": "Matthew Sherwood",
        "sub": false,
        "num_played": 3,
        "IPR": 2
      },
      {
        "key": "f61932d48e0c6de037d7e9dbca92f8138a9ca199",
        "name": "Nick Taseris",
        "sub": false,
        "num_played": 3,
        "IPR": 5
      },
      {
        "key": "fd9784352747498efd00ec5abd77bb2bc9598edf",
        "name": "Ryan Loftus",
        "sub": false,
        "num_played": 3,
        "IPR": 2
      },
      {
        "key": "2e399c30b768a8409eb1ced8e025529f0d0e80bb",
        "name": "Tom Baisden",
        "sub": false,
        "num_played": 3,
        "IPR": 1
      }
    ],
    "ready": true,
    "confirmed": {
      "by": "Scott Helgason",
      "at": 1667881989830
    }
  },
  "rounds": [
    {
      "n": 1,
      "games": [
        {
          "n": 1,
          "machine": "MM",
          "player_1": "a0a68005f40b140a03290f64bb8cd03353f48c1e",
          "player_3": "a9c6b74c710fe3b6ba45629b220c148a2003f162",
          "player_2": "b4c6f4a0222bf84e9811cf283febf386684852d5",
          "player_4": "fd9784352747498efd00ec5abd77bb2bc9598edf",
          "done": true,
          "photos": [
            {
              "uploaded_by": "a0a68005f40b140a03290f64bb8cd03353f48c1e",
              "url": "/pics/a56995f3dee2cfe554bc8e34c58450bcee3b9846",
              "rot": 0,
              "scale": 4.162564469218747,
              "dx": -306,
              "dy": -391
            }
          ],
          "score_1": 5018340,
          "score_2": 33466580,
          "score_3": 17550130,
          "score_4": 10565780,
          "points_1": 0,
          "points_2": 2.5,
          "points_3": 1,
          "points_4": 1.5,
          "score_13": 22568470,
          "score_24": 44032360,
          "points_13": 1,
          "points_24": 4,
          "away_points": 1,
          "home_points": 4
        },
        {
          "n": 2,
          "machine": "RollerGames",
          "player_1": "f9bd75da89cd62f8e95d7e0a37685da3810c8183",
          "player_3": "d2f7345141f115afae0cd9ea551018a8a7d12528",
          "player_2": "a5863561101172aa1631bd35d0911b8bd136b117",
          "player_4": "3f1d455e7fd930d2509ad908e2231f4f2ace791e",
          "done": true,
          "photos": [
            {
              "uploaded_by": "f9bd75da89cd62f8e95d7e0a37685da3810c8183",
              "url": "/pics/c6c83c0bfb2e364c1a5dbcef4305b8aeade85678",
              "rot": 0,
              "scale": 1,
              "dx": 0,
              "dy": 0
            }
          ],
          "score_1": 320090,
          "score_2": 1913320,
          "score_3": 1831390,
          "score_4": 567020,
          "points_1": 0,
          "points_2": 2.5,
          "points_3": 1,
          "points_4": 1.5,
          "score_13": 2151480,
          "score_24": 2480340,
          "points_13": 1,
          "points_24": 4,
          "away_points": 1,
          "home_points": 4
        },
        {
          "n": 3,
          "machine": "AFM",
          "player_1": "1bf098b4ddbff230efd9c925eca3322cd8461f85",
          "player_3": "666ef16d5cfc2ae722bd45643157f3c13eae0062",
          "player_2": "2e399c30b768a8409eb1ced8e025529f0d0e80bb",
          "player_4": "04fda437f422f17681c39fae5ba7d3a8e4a3282f",
          "photos": [
            {
              "uploaded_by": "666ef16d5cfc2ae722bd45643157f3c13eae0062",
              "url": "/pics/cceb09fd59d9b09cfaebe5bc04257bfbe5eaac76",
              "rot": 0,
              "scale": 2.5558777982396346,
              "dx": -11,
              "dy": -631
            }
          ],
          "score_1": 801010470,
          "score_2": 360005150,
          "score_3": 1519853350,
          "score_4": 561207960,
          "done": true,
          "points_1": 2.5,
          "points_2": 0,
          "points_3": 2.5,
          "points_4": 0,
          "score_13": 2320863820,
          "score_24": 921213110,
          "points_13": 5,
          "points_24": 0,
          "away_points": 5,
          "home_points": 0
        },
        {
          "n": 4,
          "machine": "SternPark",
          "player_1": "2f42b169d65f318007e360e5fa8e414764304e25",
          "player_3": "f69f2cc7fc9237f2685addaa14a2ae2ec8709451",
          "player_2": "f61932d48e0c6de037d7e9dbca92f8138a9ca199",
          "player_4": "db6c5cd060abb9e3a5da8370c2c3e9c0ef198a45",
          "done": true,
          "photos": [
            {
              "uploaded_by": "f69f2cc7fc9237f2685addaa14a2ae2ec8709451",
              "url": "/pics/ec454f19313c0f2bec3823badcc465c452261268",
              "rot": 0,
              "scale": 4.173165739287219,
              "dx": -270,
              "dy": -441
            }
          ],
          "score_1": 15729920,
          "score_2": 130440850,
          "score_3": 115616140,
          "score_4": 9571580,
          "points_1": 1,
          "points_2": 2.5,
          "points_3": 1,
          "points_4": 0.5,
          "score_13": 131346060,
          "score_24": 140012430,
          "points_13": 2,
          "points_24": 3,
          "away_points": 2,
          "home_points": 3
        }
      ],
      "done": true,
      "right_confirmed": {
        "by": "Dwayne Collins",
        "at": 1667884566627
      },
      "left_confirmed": {
        "by": "Maria Reidell",
        "at": 1667884581815
      }
    },
    {
      "n": 2,
      "games": [
        {
          "n": 1,
          "done": true,
          "machine": "Sopranos",
          "player_1": "e6b671979862b1ede4ab48b617b4ede86bba27bc",
          "player_2": "a9c6b74c710fe3b6ba45629b220c148a2003f162",
          "photos": [
            {
              "uploaded_by": "e6b671979862b1ede4ab48b617b4ede86bba27bc",
              "url": "/pics/74434a9bbc14441a3df407c90ab836282509888e",
              "rot": 0,
              "scale": 2.10462697445145,
              "dx": 31,
              "dy": 21
            }
          ],
          "score_1": 103890430,
          "score_2": 50880930,
          "points_1": 3,
          "points_2": 0,
          "points_13": 3,
          "points_24": 0,
          "score_13": 103890430,
          "score_24": 50880930,
          "away_points": 0,
          "home_points": 3
        },
        {
          "n": 2,
          "done": true,
          "machine": "Getaway",
          "player_1": "e10076f402847f4055455fc4d2717fc3ae14078e",
          "player_2": "d2f7345141f115afae0cd9ea551018a8a7d12528",
          "photos": [
            {
              "uploaded_by": "f69f2cc7fc9237f2685addaa14a2ae2ec8709451",
              "url": "/pics/a7ba8ab113f82a21fc7ac6793b34167fe2da9443",
              "rot": 0,
              "scale": 3.9825516045296783,
              "dx": -109,
              "dy": -513
            },
            {
              "uploaded_by": "a5863561101172aa1631bd35d0911b8bd136b117",
              "url": "/pics/87198a98d61592e62a5690c8a81e04104da2e7f4",
              "rot": 0,
              "scale": 3.7859318569656955,
              "dx": -198,
              "dy": -437
            }
          ],
          "score_1": 73555430,
          "score_2": 19236470,
          "points_1": 3,
          "points_2": 0,
          "points_13": 3,
          "points_24": 0,
          "score_13": 73555430,
          "score_24": 19236470,
          "away_points": 0,
          "home_points": 3
        },
        {
          "n": 3,
          "done": true,
          "machine": "POTC",
          "player_1": "b4c6f4a0222bf84e9811cf283febf386684852d5",
          "player_2": "a693ae0dd694c79f9af8ce9b9a3e612c8a61a4b8",
          "photos": [
            {
              "uploaded_by": "b4c6f4a0222bf84e9811cf283febf386684852d5",
              "url": "/pics/facf0834b1e6a9389c368b7cd5b706e5900cca76",
              "rot": 0,
              "scale": 2.339825666906042,
              "dx": -62,
              "dy": -467
            },
            {
              "uploaded_by": "cb2459e80c52fefe189d0b6a3dbca979c0f09ddd",
              "url": "/pics/27ab7cd3055eb7ceb10f14c9fb90043393bcd968",
              "rot": 0,
              "scale": 1.6167398008471008,
              "dx": -183,
              "dy": -215
            }
          ],
          "score_1": 35888850,
          "score_2": 6029750,
          "points_1": 3,
          "points_2": 0,
          "points_13": 3,
          "points_24": 0,
          "score_13": 35888850,
          "score_24": 6029750,
          "away_points": 0,
          "home_points": 3
        },
        {
          "n": 4,
          "done": true,
          "machine": "IronMaiden",
          "player_1": "a5863561101172aa1631bd35d0911b8bd136b117",
          "player_2": "a0a68005f40b140a03290f64bb8cd03353f48c1e",
          "photos": [
            {
              "uploaded_by": "a0a68005f40b140a03290f64bb8cd03353f48c1e",
              "url": "/pics/7ab003d8cf24d2ee985c362584078f2f2f690a4a",
              "rot": 0,
              "scale": 3.1554307558089403,
              "dx": -182,
              "dy": -446
            }
          ],
          "score_1": 155503680,
          "score_2": 47911680,
          "points_1": 3,
          "points_2": 0,
          "points_13": 3,
          "points_24": 0,
          "score_13": 155503680,
          "score_24": 47911680,
          "away_points": 0,
          "home_points": 3
        },
        {
          "n": 5,
          "done": true,
          "machine": "AFM",
          "player_1": "fd9784352747498efd00ec5abd77bb2bc9598edf",
          "player_2": "1bf098b4ddbff230efd9c925eca3322cd8461f85",
          "photos": [
            {
              "uploaded_by": "1bf098b4ddbff230efd9c925eca3322cd8461f85",
              "url": "/pics/32b65d0f586286a6c47161f0e2f3ee035e2ddd90",
              "rot": 0,
              "scale": 1,
              "dx": 126,
              "dy": -340
            }
          ],
          "score_1": 2010240620,
          "score_2": 786826560,
          "points_1": 3,
          "points_2": 0,
          "points_13": 3,
          "points_24": 0,
          "score_13": 2010240620,
          "score_24": 786826560,
          "away_points": 0,
          "home_points": 3
        },
        {
          "n": 6,
          "done": true,
          "machine": "Hotdoggin'",
          "player_1": "2e399c30b768a8409eb1ced8e025529f0d0e80bb",
          "player_2": "cb2459e80c52fefe189d0b6a3dbca979c0f09ddd",
          "photos": [
            {
              "uploaded_by": "cb2459e80c52fefe189d0b6a3dbca979c0f09ddd",
              "url": "/pics/6bcbaa465302e9ed4208b8b982be73fedd852c50",
              "rot": 0,
              "scale": 1.529293119777236,
              "dx": -95,
              "dy": -55
            }
          ],
          "score_1": 83730,
          "score_2": 137840,
          "points_1": 1,
          "points_2": 2,
          "points_13": 1,
          "points_24": 2,
          "score_13": 83730,
          "score_24": 137840,
          "away_points": 2,
          "home_points": 1
        },
        {
          "n": 7,
          "done": true,
          "machine": "Harlem",
          "player_1": "04fda437f422f17681c39fae5ba7d3a8e4a3282f",
          "player_2": "2f42b169d65f318007e360e5fa8e414764304e25",
          "photos": [
            {
              "uploaded_by": "a0a68005f40b140a03290f64bb8cd03353f48c1e",
              "url": "/pics/bef64dd79e5b38108bf2c5313378f26dcf2d6ee2",
              "rot": 0,
              "scale": 2.687327871646386,
              "dx": -141,
              "dy": -189
            }
          ],
          "score_1": 107950,
          "score_2": 147850,
          "points_1": 1,
          "points_2": 2,
          "points_13": 1,
          "points_24": 2,
          "score_13": 107950,
          "score_24": 147850,
          "away_points": 2,
          "home_points": 1
        }
      ],
      "done": true,
      "left_confirmed": {
        "by": "Jamie Winsor",
        "at": 1667887414798
      },
      "right_confirmed": {
        "by": "Maria Reidell",
        "at": 1667887440415
      }
    },
    {
      "n": 3,
      "games": [
        {
          "n": 1,
          "machine": "BKSoR",
          "player_1": "f69f2cc7fc9237f2685addaa14a2ae2ec8709451",
          "player_2": "e10076f402847f4055455fc4d2717fc3ae14078e",
          "done": true,
          "score_1": 79312720,
          "score_2": 186788950,
          "points_1": 0,
          "points_2": 3,
          "points_13": 0,
          "points_24": 3,
          "score_13": 79312720,
          "score_24": 186788950,
          "away_points": 0,
          "home_points": 3
        },
        {
          "n": 2,
          "machine": "TAF",
          "player_1": "666ef16d5cfc2ae722bd45643157f3c13eae0062",
          "player_2": "db6c5cd060abb9e3a5da8370c2c3e9c0ef198a45",
          "done": true,
          "photos": [
            {
              "uploaded_by": "666ef16d5cfc2ae722bd45643157f3c13eae0062",
              "url": "/pics/3168eda1b4994a715a3af95bc1f6556e49821ff0",
              "rot": 0,
              "scale": 1.6860307321338963,
              "dx": 53,
              "dy": 0
            }
          ],
          "score_1": 75546310,
          "score_2": 17723880,
          "points_1": 3,
          "points_2": 0,
          "points_13": 3,
          "points_24": 0,
          "score_13": 75546310,
          "score_24": 17723880,
          "away_points": 3,
          "home_points": 0
        },
        {
          "n": 3,
          "machine": "Hotdoggin'",
          "player_1": "a693ae0dd694c79f9af8ce9b9a3e612c8a61a4b8",
          "player_2": "b4c6f4a0222bf84e9811cf283febf386684852d5",
          "done": true,
          "score_1": 229290,
          "score_2": 810580,
          "points_1": 0,
          "points_2": 3,
          "points_13": 0,
          "points_24": 3,
          "score_13": 229290,
          "score_24": 810580,
          "away_points": 0,
          "home_points": 3
        },
        {
          "n": 4,
          "machine": "Embryon",
          "player_1": "cb2459e80c52fefe189d0b6a3dbca979c0f09ddd",
          "player_2": "f61932d48e0c6de037d7e9dbca92f8138a9ca199",
          "photos": [
            {
              "uploaded_by": "cb2459e80c52fefe189d0b6a3dbca979c0f09ddd",
              "url": "/pics/59720a27ba2ac56dafd1720178d9052d4b4278f1",
              "rot": 0,
              "scale": 1.4944542956436973,
              "dx": -220,
              "dy": -76
            }
          ],
          "score_1": 172060,
          "score_2": 89600,
          "done": true,
          "points_1": 2,
          "points_2": 1,
          "points_13": 2,
          "points_24": 1,
          "score_13": 172060,
          "score_24": 89600,
          "away_points": 2,
          "home_points": 1
        },
        {
          "n": 5,
          "machine": "StrangerThings",
          "player_1": "1bf098b4ddbff230efd9c925eca3322cd8461f85",
          "player_2": "e6b671979862b1ede4ab48b617b4ede86bba27bc",
          "done": true,
          "photos": [
            {
              "uploaded_by": "e6b671979862b1ede4ab48b617b4ede86bba27bc",
              "url": "/pics/e6362cecb0cf2cba9e1c0882f7e07398b2df316d",
              "rot": 0,
              "scale": 1.98023710672737,
              "dx": -4,
              "dy": 43
            }
          ],
          "score_1": 47397110,
          "score_2": 49089850,
          "points_1": 1,
          "points_2": 2,
          "points_13": 1,
          "points_24": 2,
          "score_13": 47397110,
          "score_24": 49089850,
          "away_points": 1,
          "home_points": 2
        },
        {
          "n": 6,
          "machine": "FT",
          "player_1": "d2f7345141f115afae0cd9ea551018a8a7d12528",
          "player_2": "3f1d455e7fd930d2509ad908e2231f4f2ace791e",
          "done": true,
          "photos": [
            {
              "uploaded_by": "3f1d455e7fd930d2509ad908e2231f4f2ace791e",
              "url": "/pics/cdae9530d640bdd5118dcfc87b814fe311016b25",
              "rot": 0,
              "scale": 2.821195228054613,
              "dx": -113,
              "dy": -317
            }
          ],
          "score_1": 4395900,
          "score_2": 13483970,
          "points_1": 0,
          "points_2": 3,
          "points_13": 0,
          "points_24": 3,
          "score_13": 4395900,
          "score_24": 13483970,
          "away_points": 0,
          "home_points": 3
        },
        {
          "n": 7,
          "machine": "BSD",
          "player_1": "f9bd75da89cd62f8e95d7e0a37685da3810c8183",
          "player_2": "a5863561101172aa1631bd35d0911b8bd136b117",
          "done": true,
          "photos": [
            {
              "uploaded_by": "a5863561101172aa1631bd35d0911b8bd136b117",
              "url": "/pics/d5c696b0e6bf0ccbaa8378b71b58dc55686bbcd5",
              "rot": 0,
              "scale": 2.8094539462647297,
              "dx": -176,
              "dy": -477
            }
          ],
          "score_1": 10002510,
          "score_2": 274967070,
          "points_1": 0,
          "points_2": 3,
          "points_13": 0,
          "points_24": 3,
          "score_13": 10002510,
          "score_24": 274967070,
          "away_points": 0,
          "home_points": 3
        }
      ],
      "done": true,
      "right_confirmed": {
        "by": "Jamie Winsor",
        "at": 1667889685279
      },
      "left_confirmed": {
        "by": "Maria Reidell",
        "at": 1667889694632
      }
    },
    {
      "n": 4,
      "games": [
        {
          "n": 1,
          "done": true,
          "machine": "Getaway",
          "player_1": "e10076f402847f4055455fc4d2717fc3ae14078e",
          "player_3": "04fda437f422f17681c39fae5ba7d3a8e4a3282f",
          "player_2": "2f42b169d65f318007e360e5fa8e414764304e25",
          "player_4": "f9bd75da89cd62f8e95d7e0a37685da3810c8183",
          "photos": [
            {
              "uploaded_by": "a5863561101172aa1631bd35d0911b8bd136b117",
              "url": "/pics/17d6907e318f7047e7809fb091887c0aae8b2160",
              "rot": 0,
              "scale": 5.590675316999067,
              "dx": -311,
              "dy": -318
            },
            {
              "uploaded_by": "3f1d455e7fd930d2509ad908e2231f4f2ace791e",
              "url": "/pics/06b8154a3eb8a4dec3387072d6b5d9af9801678a",
              "rot": 0,
              "scale": 2.155142942191601,
              "dx": -377,
              "dy": -276
            }
          ],
          "score_1": 147207710,
          "score_2": 18911850,
          "score_3": 58879420,
          "score_4": 44482240,
          "points_1": 2.5,
          "points_2": 0,
          "points_3": 2.5,
          "points_4": 0,
          "score_13": 206087130,
          "score_24": 63394090,
          "points_13": 5,
          "points_24": 0,
          "away_points": 0,
          "home_points": 5
        },
        {
          "n": 2,
          "done": true,
          "machine": "Sopranos",
          "player_1": "f61932d48e0c6de037d7e9dbca92f8138a9ca199",
          "player_3": "e6b671979862b1ede4ab48b617b4ede86bba27bc",
          "player_2": "a693ae0dd694c79f9af8ce9b9a3e612c8a61a4b8",
          "player_4": "a9c6b74c710fe3b6ba45629b220c148a2003f162",
          "photos": [
            {
              "uploaded_by": "e6b671979862b1ede4ab48b617b4ede86bba27bc",
              "url": "/pics/a27fd5e6eab0b4cd5f65348c798905f6910c75a4",
              "rot": 0,
              "scale": 1.805096567717232,
              "dx": 24,
              "dy": 22
            }
          ],
          "score_1": 102920320,
          "score_2": 38768250,
          "score_3": 38794930,
          "score_4": 19073290,
          "points_1": 2.5,
          "points_2": 0,
          "points_3": 2.5,
          "points_4": 0,
          "score_13": 141715250,
          "score_24": 57841540,
          "points_13": 5,
          "points_24": 0,
          "away_points": 0,
          "home_points": 5
        },
        {
          "n": 3,
          "done": true,
          "machine": "AFM",
          "player_1": "db6c5cd060abb9e3a5da8370c2c3e9c0ef198a45",
          "player_3": "3f1d455e7fd930d2509ad908e2231f4f2ace791e",
          "player_2": "f69f2cc7fc9237f2685addaa14a2ae2ec8709451",
          "player_4": "a0a68005f40b140a03290f64bb8cd03353f48c1e",
          "photos": [
            {
              "uploaded_by": "a0a68005f40b140a03290f64bb8cd03353f48c1e",
              "url": "/pics/06f9458a9a76105514c25f6cf53dec2bc7e0d600",
              "rot": 0,
              "scale": 2.68213140181848,
              "dx": -121,
              "dy": -304
            }
          ],
          "score_1": 3751625240,
          "score_2": 4364349030,
          "score_3": 2132301930,
          "score_4": 2241436730,
          "points_1": 1,
          "points_2": 2.5,
          "points_3": 0,
          "points_4": 1.5,
          "score_13": 5883927170,
          "score_24": 6605785760,
          "points_13": 1,
          "points_24": 4,
          "away_points": 4,
          "home_points": 1
        },
        {
          "n": 4,
          "done": true,
          "machine": "Harlem",
          "player_1": "fd9784352747498efd00ec5abd77bb2bc9598edf",
          "player_3": "2e399c30b768a8409eb1ced8e025529f0d0e80bb",
          "player_2": "666ef16d5cfc2ae722bd45643157f3c13eae0062",
          "player_4": "cb2459e80c52fefe189d0b6a3dbca979c0f09ddd",
          "photos": [
            {
              "uploaded_by": "cb2459e80c52fefe189d0b6a3dbca979c0f09ddd",
              "url": "/pics/f95f17f2563dd66bfdd69803b3b0caf539d480c9",
              "rot": 0,
              "scale": 1.584366050614974,
              "dx": -173,
              "dy": -145
            }
          ],
          "score_1": 854740,
          "score_2": 113960,
          "score_3": 242130,
          "score_4": 250680,
          "points_1": 2.5,
          "points_2": 0,
          "points_3": 1.5,
          "points_4": 1,
          "score_13": 1096870,
          "score_24": 364640,
          "points_13": 4,
          "points_24": 1,
          "away_points": 1,
          "home_points": 4
        }
      ],
      "done": true,
      "left_confirmed": {
        "by": "Dwayne Collins",
        "at": 1667893541261
      },
      "right_confirmed": {
        "by": "Maria Reidell",
        "at": 1667893655075
      }
    }
  ],
  "players": []
}