{
  "key": "mnp-14-7-LCS-RMS",
  "name": "WK7 LCS @ RMS",
  "type": "manual",
  "week": "7",
  "round": 4,
  "create_at": 1635203398491,
  "date": "10/25/2021",
  "state": "complete",
  "venue": {
    "key": "RAY",
    "name": "Raygun Lounge",
    "machines": [
      "DND",
      "JM",
      "DM",
      "Guardians",
      "Shadow",
      "T2",
      "AFM",
      "MarsTrek",
      "AIQ",
      "SternPark",
      "DP"
    ]
  },
  "away": {
    "name": "Lake City Shooters",
    "key": "LCS",
    "captains": [
      {
        "key": "5e26c52b2ab09f2a19576af1389327e974056883",
        "name": "Mitchell D. Anderson"
      },
      {
        "key": "4da2f815d7ba14404d49f7a463ec97621b7bc47a",
        "name": "John Robinson WA"
      }
    ],
    "lineup": [
      {
        "key": "8a95c98c3ac0176c7ec366588af14f49b9a23ca9",
        "name": "Dan Danger",
        "sub": false,
        "num_played": 0,
        "IPR": 3
      },
      {
        "key": "096e97b8eca3ee52f5026b3f51b49ef81673eeb3",
        "name": "Eric Morales",
        "sub": false,
        "num_played": 0,
        "IPR": 5
      },
      {
        "key": "0fee9a03c4e9da4416c7c4ce42bf1f100d4b02ba",
        "name": "Frankie Fingers",
        "sub": false,
        "num_played": 0,
        "IPR": 3
      },
      {
        "key": "90a31f972a8c26ed6f70097f1230bd7feedb1301",
        "name": "John McConnell",
        "sub": false,
        "num_played": 0,
        "IPR": 3
      },
      {
        "key": "4da2f815d7ba14404d49f7a463ec97621b7bc47a",
        "name": "John Robinson WA",
        "sub": false,
        "num_played": 0,
        "IPR": 6
      },
      {
        "key": "816420e671276840f9366d3ca3651a6505473efc",
        "name": "Katie Janis",
        "sub": false,
        "num_played": 0,
        "IPR": 2
      },
      {
        "key": "690c71953dc1d8a29beca4fc64222ac72e1b2829",
        "name": "Kay Kay",
        "sub": false,
        "num_played": 0,
        "IPR": 1
      },
      {
        "key": "5e26c52b2ab09f2a19576af1389327e974056883",
        "name": "Mitchell D. Anderson",
        "sub": false,
        "num_played": 0,
        "IPR": 5
      },
      {
        "key": "064ee1caf47c445e16f4c394684cf6345464f70a",
        "name": "Pony Hurlbert",
        "sub": false,
        "num_played": 0,
        "IPR": 1
      }
    ]
  },
  "home": {
    "name": "Magic Saves",
    "key": "RMS",
    "captains": [
      {
        "key": "22aca18161115992ebe2c6a87e963c2d947e7ca4",
        "name": "Zolaire Arcade"
      },
      {
        "key": "fbada9b3d072be51395b2dece73221d119c44294",
        "name": "Michael Zuino"
      }
    ],
    "lineup": [
      {
        "key": "d296a2637a2d03fef72e3d206a85a8946157e59a",
        "name": "Andrew Hopper",
        "sub": false,
        "num_played": 0,
        "IPR": 3
      },
      {
        "key": "1310b61afc040d2e03f5669c6a0ebdd72c56c439",
        "name": "Andy Meuser",
        "sub": false,
        "num_played": 0,
        "IPR": 1
      },
      {
        "key": "0885d316f4c017359859daafb905df891d485fe8",
        "name": "Jake Beckerman",
        "sub": false,
        "num_played": 0,
        "IPR": 2
      },
      {
        "key": "b2b610550300bdc57f39e72ca66d0a6d8a6c9168",
        "name": "Josh Schaffner",
        "sub": false,
        "num_played": 0,
        "IPR": 1
      },
      {
        "key": "fbada9b3d072be51395b2dece73221d119c44294",
        "name": "Michael Zuino",
        "sub": false,
        "num_played": 0,
        "IPR": 2
      },
      {
        "key": "5b36a61d31157cb214bfb7abd0d387edd8c16afb",
        "name": "Pat Salembier",
        "sub": false,
        "num_played": 0,
        "IPR": 1
      },
      {
        "key": "032cfc3f5bead0242dfaa3e06584d84e9b9da059",
        "name": "Randy Huynh",
        "sub": false,
        "num_played": 0,
        "IPR": 2
      },
      {
        "key": "bfd3da60feb11490da1d4b989d7eebdeffd2c07e",
        "name": "Rita Perez",
        "sub": false,
        "num_played": 0,
        "IPR": 1
      },
      {
        "key": "22aca18161115992ebe2c6a87e963c2d947e7ca4",
        "name": "Zolaire Arcade",
        "sub": false,
        "num_played": 0,
        "IPR": 2
      }
    ],
    "ready": true,
    "confirmed": false
  },
  "rounds": [
    {
      "n": 1,
      "games": [
        {
          "n": 1,
          "away_points": 0,
          "home_points": 2
        },
        {
          "n": 2,
          "away_points": 0,
          "home_points": 2
        },
        {
          "n": 3,
          "away_points": 0,
          "home_points": 2
        },
        {
          "n": 4,
          "away_points": 0,
          "home_points": 10
        }
      ],
      "done": true
    },
    {
      "n": 2,
      "games": [
        {
          "n": 1,
          "away_points": 0,
          "home_points": 2
        },
        {
          "n": 2,
          "away_points": 0,
          "home_points": 2
        },
        {
          "n": 3,
          "away_points": 0,
          "home_points": 2
        },
        {
          "n": 4,
          "away_points": 0,
          "home_points": 2
        },
        {
          "n": 5,
          "away_points": 0,
          "home_points": 2
        },
        {
          "n": 6,
          "away_points": 0,
          "home_points": 2
        },
        {
          "n": 7,
          "away_points": 0,
          "home_points": 2
        }
      ],
      "done": true
    },
    {
      "n": 3,
      "games": [
        {
          "n": 1,
          "away_points": 0,
          "home_points": 2
        },
        {
          "n": 2,
          "away_points": 0,
          "home_points": 2
        },
        {
          "n": 3,
          "away_points": 0,
          "home_points": 2
        },
        {
          "n": 4,
          "away_points": 0,
          "home_points": 2
        },
        {
          "n": 5,
          "away_points": 0,
          "home_points": 2
        },
        {
          "n": 6,
          "away_points": 0,
          "home_points": 2
        },
        {
          "n": 7,
          "away_points": 0,
          "home_points": 2
        }
      ],
      "done": true
    },
    {
      "n": 4,
      "games": [
        {
          "n": 1,
          "away_points": 0,
          "home_points": 2
        },
        {
          "n": 2,
          "away_points": 0,
          "home_points": 2
        },
        {
          "n": 3,
          "away_points": 0,
          "home_points": 3
        },
        {
          "n": 4,
          "away_points": 0,
          "home_points": 10
        }
      ],
      "done": true
    }
  ],
  "players": []
}