{
  "key": "mnp-19-9-PKT-DTP",
  "name": "WK9 PKT @ DTP",
  "type": "manual",
  "week": "9",
  "round": 4,
  "create_at": 1712461746014,
  "date": "04/08/2024",
  "state": "complete",
  "venue": {
    "key": "JUP",
    "name": "Jupiter",
    "machines": [
      "Jaws",
      "Venom",
      "FOO",
      "Sopranos",
      "CactusCanyon",
      "James Bond '007",
      "Godzilla",
      "StrangerThings",
      "WCS",
      "POTC",
      "BKSoR",
      "SternPark",
      "SternTrek",
      "BSD",
      "IronMaiden",
      "Getaway",
      "Harlem",
      "AFM",
      "GOT",
      "SpaceInvaders",
      "TAF",
      "FT",
      "MM",
      "Paragon",
      "MB",
      "Metallica",
      "Hotdoggin'",
      "Future Spa",
      "Embryon"
    ]
  },
  "away": {
    "name": "Pocketeers",
    "key": "PKT",
    "captains": [
      {
        "key": "f3236eec1d002a53ef688d10e6260d7d6892822d",
        "name": "Emily Young"
      },
      {
        "key": "ba7a448938446d3988e66b84d9e89244cf0f593b",
        "name": "Lonnie Langford"
      }
    ],
    "lineup": [
      {
        "key": "4189497fc83adf0cb6ce5b3d0ba8daf2957c828e",
        "name": "Amber Roy",
        "sub": false,
        "num_played": 3,
        "IPR": 4
      },
      {
        "key": "9288e48ded0c4745ed02dc6a032fb2908c2a9ee8",
        "name": "Chris Vela",
        "sub": false,
        "num_played": 3,
        "IPR": 3
      },
      {
        "key": "a2cd3a6ca9ddd8969b9aa102b742581b73a618b4",
        "name": "Elena Wright",
        "sub": false,
        "num_played": 3,
        "IPR": 3
      },
      {
        "key": "f3236eec1d002a53ef688d10e6260d7d6892822d",
        "name": "Emily Young",
        "sub": false,
        "num_played": 3,
        "IPR": 3
      },
      {
        "key": "5c8d706cf4d567fcd2f10c866b86e46aac378cef",
        "name": "James Pink",
        "sub": true,
        "IPR": 3,
        "num_played": 3
      },
      {
        "key": "72419e2737795e2014538d8458f8ec684c03c8aa",
        "name": "Kelsie Sherman Hall",
        "sub": false,
        "num_played": 3,
        "IPR": 2
      },
      {
        "key": "ba7a448938446d3988e66b84d9e89244cf0f593b",
        "name": "Lonnie Langford",
        "sub": false,
        "num_played": 3,
        "IPR": 6
      },
      {
        "key": "4ed2b0e003f24802a96cef98de1279858e3b49b9",
        "name": "Nick Filer",
        "sub": false,
        "num_played": 3,
        "IPR": 3
      },
      {
        "key": "bb95ce373c39640f64e21ddea6a8a1c43a410866",
        "name": "Randall Olson",
        "sub": false,
        "num_played": 3,
        "IPR": 1
      },
      {
        "key": "4591efba4cc775cea81f4e9be70510cccaf22e96",
        "name": "Ryan Tamm",
        "sub": true,
        "IPR": 2,
        "num_played": 3
      }
    ],
    "ready": true,
    "confirmed": {
      "by": "Dwayne Collins",
      "at": 1712631572794
    }
  },
  "home": {
    "name": "DTP",
    "key": "DTP",
    "captains": [
      {
        "key": "3f1d455e7fd930d2509ad908e2231f4f2ace791e",
        "name": "Dwayne Collins"
      },
      {
        "key": "a5863561101172aa1631bd35d0911b8bd136b117",
        "name": "Kevin Coffey"
      }
    ],
    "lineup": [
      {
        "key": "04fda437f422f17681c39fae5ba7d3a8e4a3282f",
        "name": "Alex Hawley",
        "sub": false,
        "num_played": 3,
        "IPR": 3
      },
      {
        "key": "b4c6f4a0222bf84e9811cf283febf386684852d5",
        "name": "Alex Skinner",
        "sub": false,
        "num_played": 3,
        "IPR": 5
      },
      {
        "key": "f0ce5558555263c7774a8960e0df78b6e8ec1000",
        "name": "Camille Funk",
        "sub": true,
        "IPR": 1,
        "num_played": 3
      },
      {
        "key": "3f1d455e7fd930d2509ad908e2231f4f2ace791e",
        "name": "Dwayne Collins",
        "sub": false,
        "num_played": 3,
        "IPR": 2
      },
      {
        "key": "a5863561101172aa1631bd35d0911b8bd136b117",
        "name": "Kevin Coffey",
        "sub": false,
        "IPR": 5,
        "num_played": 3
      },
      {
        "key": "e10076f402847f4055455fc4d2717fc3ae14078e",
        "name": "Kristin Vick",
        "sub": false,
        "num_played": 3,
        "IPR": 4
      },
      {
        "key": "f61932d48e0c6de037d7e9dbca92f8138a9ca199",
        "name": "Nick Taseris",
        "sub": false,
        "num_played": 3,
        "IPR": 5
      },
      {
        "key": "fd9784352747498efd00ec5abd77bb2bc9598edf",
        "name": "Ryan Loftus",
        "sub": false,
        "num_played": 3,
        "IPR": 1
      },
      {
        "key": "b4a2f16cda41f8d19e3fe6acc7f3abbaeb751fd3",
        "name": "Stephen Chism",
        "sub": true,
        "IPR": 0,
        "num_played": 3
      },
      {
        "key": "2e399c30b768a8409eb1ced8e025529f0d0e80bb",
        "name": "Tom Baisden",
        "sub": false,
        "num_played": 3,
        "IPR": 2
      }
    ],
    "ready": true,
    "confirmed": {
      "by": "Emily Young",
      "at": 1712631839293
    }
  },
  "rounds": [
    {
      "n": 1,
      "games": [
        {
          "n": 1,
          "machine": "AFM",
          "player_1": "a2cd3a6ca9ddd8969b9aa102b742581b73a618b4",
          "player_3": "4189497fc83adf0cb6ce5b3d0ba8daf2957c828e",
          "player_2": "fd9784352747498efd00ec5abd77bb2bc9598edf",
          "player_4": "2e399c30b768a8409eb1ced8e025529f0d0e80bb",
          "done": true,
          "photos": [
            {
              "uploaded_by": "4189497fc83adf0cb6ce5b3d0ba8daf2957c828e",
              "url": "/pics/5f6c672601b2f33d694bae0930b68e5def6c0f8f",
              "rot": 0,
              "scale": 2.3793323663797916,
              "dx": -543,
              "dy": -272
            }
          ],
          "score_1": 4315801070,
          "score_2": 943450100,
          "score_3": 1607127270,
          "score_4": 3072101530,
          "points_1": 2.5,
          "points_2": 0,
          "points_3": 1.5,
          "points_4": 1,
          "score_13": 5922928340,
          "score_24": 4015551630,
          "points_13": 4,
          "points_24": 1,
          "away_points": 4,
          "home_points": 1
        },
        {
          "n": 2,
          "machine": "FT",
          "player_1": "f3236eec1d002a53ef688d10e6260d7d6892822d",
          "player_3": "72419e2737795e2014538d8458f8ec684c03c8aa",
          "player_2": "b4a2f16cda41f8d19e3fe6acc7f3abbaeb751fd3",
          "player_4": "b4c6f4a0222bf84e9811cf283febf386684852d5",
          "photos": [
            {
              "uploaded_by": "b4c6f4a0222bf84e9811cf283febf386684852d5",
              "url": "/pics/9c2bd70dea12581cc42dbf765f21d1ebd71c6326",
              "rot": 0,
              "scale": 1.712772014709375,
              "dx": -218,
              "dy": -265
            }
          ],
          "score_1": 29488520,
          "score_2": 4033700,
          "score_3": 3617260,
          "score_4": 85479150,
          "done": true,
          "points_1": 1,
          "points_2": 1.5,
          "points_3": 0,
          "points_4": 2.5,
          "score_13": 33105780,
          "score_24": 89512850,
          "points_13": 1,
          "points_24": 4,
          "away_points": 1,
          "home_points": 4
        },
        {
          "n": 3,
          "machine": "MM",
          "player_1": "4ed2b0e003f24802a96cef98de1279858e3b49b9",
          "player_3": "bb95ce373c39640f64e21ddea6a8a1c43a410866",
          "player_2": "e10076f402847f4055455fc4d2717fc3ae14078e",
          "player_4": "f0ce5558555263c7774a8960e0df78b6e8ec1000",
          "done": true,
          "score_1": 5340210,
          "score_2": 5555050,
          "score_3": 3427770,
          "score_4": 5292260,
          "points_1": 1,
          "points_2": 2.5,
          "points_3": 0,
          "points_4": 1.5,
          "score_13": 8767980,
          "score_24": 10847310,
          "points_13": 1,
          "points_24": 4,
          "away_points": 1,
          "home_points": 4
        },
        {
          "n": 4,
          "machine": "SternTrek",
          "player_1": "9288e48ded0c4745ed02dc6a032fb2908c2a9ee8",
          "player_3": "ba7a448938446d3988e66b84d9e89244cf0f593b",
          "player_2": "f61932d48e0c6de037d7e9dbca92f8138a9ca199",
          "player_4": "04fda437f422f17681c39fae5ba7d3a8e4a3282f",
          "done": true,
          "score_1": 16057150,
          "score_2": 28351800,
          "score_3": 81477260,
          "score_4": 81446140,
          "points_1": 0,
          "points_2": 1.5,
          "points_3": 2,
          "points_4": 1.5,
          "score_13": 97534410,
          "score_24": 109797940,
          "points_13": 2,
          "points_24": 3,
          "away_points": 2,
          "home_points": 3
        }
      ],
      "done": true,
      "right_confirmed": {
        "by": "Dwayne Collins",
        "at": 1712635251580
      },
      "left_confirmed": {
        "by": "Emily Young",
        "at": 1712635264182
      }
    },
    {
      "n": 2,
      "games": [
        {
          "n": 1,
          "machine": "BKSoR",
          "player_1": "3f1d455e7fd930d2509ad908e2231f4f2ace791e",
          "player_2": "a2cd3a6ca9ddd8969b9aa102b742581b73a618b4",
          "done": true,
          "score_1": 13498690,
          "score_2": 100857100,
          "points_1": 0,
          "points_2": 3,
          "points_13": 0,
          "points_24": 3,
          "score_13": 13498690,
          "score_24": 100857100,
          "away_points": 3,
          "home_points": 0
        },
        {
          "n": 2,
          "machine": "Venom",
          "player_1": "b4c6f4a0222bf84e9811cf283febf386684852d5",
          "player_2": "ba7a448938446d3988e66b84d9e89244cf0f593b",
          "done": true,
          "score_1": 18000000,
          "score_2": 53000000,
          "points_1": 0,
          "points_2": 3,
          "points_13": 0,
          "points_24": 3,
          "score_13": 18000000,
          "score_24": 53000000,
          "away_points": 3,
          "home_points": 0
        },
        {
          "n": 3,
          "machine": "Jaws",
          "player_1": "f61932d48e0c6de037d7e9dbca92f8138a9ca199",
          "player_2": "72419e2737795e2014538d8458f8ec684c03c8aa",
          "done": true,
          "score_1": 68000000,
          "score_2": 43000000,
          "points_1": 2,
          "points_2": 1,
          "points_13": 2,
          "points_24": 1,
          "score_13": 68000000,
          "score_24": 43000000,
          "away_points": 1,
          "home_points": 2
        },
        {
          "n": 4,
          "machine": "POTC",
          "player_1": "a5863561101172aa1631bd35d0911b8bd136b117",
          "player_2": "5c8d706cf4d567fcd2f10c866b86e46aac378cef",
          "done": true,
          "score_1": 53000000,
          "score_2": 3300000,
          "points_1": 3,
          "points_2": 0,
          "points_13": 3,
          "points_24": 0,
          "score_13": 53000000,
          "score_24": 3300000,
          "away_points": 0,
          "home_points": 3
        },
        {
          "n": 5,
          "machine": "Harlem",
          "player_1": "b4a2f16cda41f8d19e3fe6acc7f3abbaeb751fd3",
          "player_2": "9288e48ded0c4745ed02dc6a032fb2908c2a9ee8",
          "done": true,
          "score_1": 208580,
          "score_2": 299650,
          "points_1": 1,
          "points_2": 2,
          "points_13": 1,
          "points_24": 2,
          "score_13": 208580,
          "score_24": 299650,
          "away_points": 2,
          "home_points": 1
        },
        {
          "n": 6,
          "machine": "Paragon",
          "player_1": "f0ce5558555263c7774a8960e0df78b6e8ec1000",
          "player_2": "bb95ce373c39640f64e21ddea6a8a1c43a410866",
          "score_1": 44910,
          "score_2": 134840,
          "done": true,
          "points_1": 0,
          "points_2": 3,
          "points_13": 0,
          "points_24": 3,
          "score_13": 44910,
          "score_24": 134840,
          "away_points": 3,
          "home_points": 0
        },
        {
          "n": 7,
          "machine": "CactusCanyon",
          "player_1": "2e399c30b768a8409eb1ced8e025529f0d0e80bb",
          "player_2": "4591efba4cc775cea81f4e9be70510cccaf22e96",
          "done": true,
          "score_1": 5130270,
          "score_2": 17599120,
          "points_1": 0,
          "points_2": 3,
          "points_13": 0,
          "points_24": 3,
          "score_13": 5130270,
          "score_24": 17599120,
          "away_points": 3,
          "home_points": 0
        }
      ],
      "done": true,
      "right_confirmed": {
        "by": "Emily Young",
        "at": 1712637101876
      },
      "left_confirmed": {
        "by": "Kevin Coffey",
        "at": 1712637271357
      }
    },
    {
      "n": 3,
      "games": [
        {
          "n": 1,
          "machine": "CactusCanyon",
          "player_1": "4591efba4cc775cea81f4e9be70510cccaf22e96",
          "player_2": "a5863561101172aa1631bd35d0911b8bd136b117",
          "done": true,
          "score_1": 10000000,
          "score_2": 30000000,
          "points_1": 0,
          "points_2": 3,
          "points_13": 0,
          "points_24": 3,
          "score_13": 10000000,
          "score_24": 30000000,
          "away_points": 0,
          "home_points": 3
        },
        {
          "n": 2,
          "machine": "Harlem",
          "player_1": "5c8d706cf4d567fcd2f10c866b86e46aac378cef",
          "player_2": "04fda437f422f17681c39fae5ba7d3a8e4a3282f",
          "done": true,
          "score_1": 350030,
          "score_2": 222150,
          "points_1": 2,
          "points_2": 1,
          "points_13": 2,
          "points_24": 1,
          "score_13": 350030,
          "score_24": 222150,
          "away_points": 2,
          "home_points": 1
        },
        {
          "n": 3,
          "machine": "Getaway",
          "player_1": "4189497fc83adf0cb6ce5b3d0ba8daf2957c828e",
          "player_2": "e10076f402847f4055455fc4d2717fc3ae14078e",
          "photos": [
            {
              "uploaded_by": "4189497fc83adf0cb6ce5b3d0ba8daf2957c828e",
              "url": "/pics/ddee8c7e92ea51a93fe782f21527aaa834b89b07",
              "rot": 0,
              "scale": 1.8803511950994412,
              "dx": -458,
              "dy": -103
            }
          ],
          "score_1": 14809560,
          "score_2": 19769290,
          "done": true,
          "points_1": 1,
          "points_2": 2,
          "points_13": 1,
          "points_24": 2,
          "score_13": 14809560,
          "score_24": 19769290,
          "away_points": 1,
          "home_points": 2
        },
        {
          "n": 4,
          "machine": "WCS",
          "player_1": "4ed2b0e003f24802a96cef98de1279858e3b49b9",
          "player_2": "fd9784352747498efd00ec5abd77bb2bc9598edf",
          "done": true,
          "score_1": 243000000,
          "score_2": 277000000,
          "points_1": 1,
          "points_2": 2,
          "points_13": 1,
          "points_24": 2,
          "score_13": 243000000,
          "score_24": 277000000,
          "away_points": 1,
          "home_points": 2
        },
        {
          "n": 5,
          "machine": "Paragon",
          "player_1": "bb95ce373c39640f64e21ddea6a8a1c43a410866",
          "player_2": "3f1d455e7fd930d2509ad908e2231f4f2ace791e",
          "done": true,
          "score_2": 30000,
          "points_1": 0,
          "points_2": 3,
          "points_3": 0,
          "points_4": 0,
          "points_13": 0,
          "points_24": 3,
          "score_13": 10000,
          "score_24": 30000,
          "score_1": 10000,
          "away_points": 0,
          "home_points": 3
        },
        {
          "n": 6,
          "machine": "FT",
          "player_1": "f3236eec1d002a53ef688d10e6260d7d6892822d",
          "player_2": "b4a2f16cda41f8d19e3fe6acc7f3abbaeb751fd3",
          "done": true,
          "score_1": 15000000,
          "score_2": 5000000,
          "points_1": 3,
          "points_2": 0,
          "points_13": 3,
          "points_24": 0,
          "score_13": 15000000,
          "score_24": 5000000,
          "away_points": 3,
          "home_points": 0
        },
        {
          "n": 7,
          "machine": "TAF",
          "player_1": "9288e48ded0c4745ed02dc6a032fb2908c2a9ee8",
          "player_2": "f61932d48e0c6de037d7e9dbca92f8138a9ca199",
          "done": true,
          "score_1": 11000000,
          "score_2": 232000000,
          "points_1": 0,
          "points_2": 3,
          "points_13": 0,
          "points_24": 3,
          "score_13": 11000000,
          "score_24": 232000000,
          "away_points": 0,
          "home_points": 3
        }
      ],
      "done": true,
      "right_confirmed": {
        "by": "Dwayne Collins",
        "at": 1712639350037
      },
      "left_confirmed": {
        "by": "Emily Young",
        "at": 1712639376187
      }
    },
    {
      "n": 4,
      "games": [
        {
          "n": 1,
          "machine": "Hotdoggin'",
          "player_1": "fd9784352747498efd00ec5abd77bb2bc9598edf",
          "player_3": "2e399c30b768a8409eb1ced8e025529f0d0e80bb",
          "player_2": "a2cd3a6ca9ddd8969b9aa102b742581b73a618b4",
          "player_4": "4ed2b0e003f24802a96cef98de1279858e3b49b9",
          "done": true,
          "score_1": 350540,
          "score_2": 186700,
          "score_3": 252160,
          "score_4": 622820,
          "points_1": 1,
          "points_2": 0.5,
          "points_3": 1,
          "points_4": 2.5,
          "score_13": 602700,
          "score_24": 809520,
          "points_13": 2,
          "points_24": 3,
          "away_points": 3,
          "home_points": 2
        },
        {
          "n": 2,
          "machine": "Embryon",
          "player_1": "04fda437f422f17681c39fae5ba7d3a8e4a3282f",
          "player_3": "f0ce5558555263c7774a8960e0df78b6e8ec1000",
          "player_2": "f3236eec1d002a53ef688d10e6260d7d6892822d",
          "player_4": "4189497fc83adf0cb6ce5b3d0ba8daf2957c828e",
          "score_1": 354900,
          "score_2": 119820,
          "score_3": 161970,
          "score_4": 25530,
          "done": true,
          "points_1": 2.5,
          "points_2": 0,
          "points_3": 2.5,
          "points_4": 0,
          "score_13": 516870,
          "score_24": 145350,
          "points_13": 5,
          "points_24": 0,
          "away_points": 0,
          "home_points": 5
        },
        {
          "n": 3,
          "machine": "Jaws",
          "player_1": "b4c6f4a0222bf84e9811cf283febf386684852d5",
          "player_3": "a5863561101172aa1631bd35d0911b8bd136b117",
          "player_2": "72419e2737795e2014538d8458f8ec684c03c8aa",
          "player_4": "5c8d706cf4d567fcd2f10c866b86e46aac378cef",
          "done": true,
          "score_1": 117000000,
          "score_2": 34000000,
          "score_3": 99000000,
          "score_4": 67000000,
          "points_1": 2.5,
          "points_2": 0,
          "points_3": 2.5,
          "points_4": 0,
          "score_13": 216000000,
          "score_24": 101000000,
          "points_13": 5,
          "points_24": 0,
          "away_points": 0,
          "home_points": 5
        },
        {
          "n": 4,
          "machine": "Sopranos",
          "player_1": "e10076f402847f4055455fc4d2717fc3ae14078e",
          "player_3": "3f1d455e7fd930d2509ad908e2231f4f2ace791e",
          "player_2": "4591efba4cc775cea81f4e9be70510cccaf22e96",
          "player_4": "ba7a448938446d3988e66b84d9e89244cf0f593b",
          "done": true,
          "photos": [
            {
              "uploaded_by": "ba7a448938446d3988e66b84d9e89244cf0f593b",
              "url": "/pics/4f23a0bb06b7ed7032d6674bce920dcbcf47bdf7",
              "rot": 0,
              "scale": 1.8777446053472913,
              "dx": -228,
              "dy": -90
            }
          ],
          "score_1": 13271660,
          "score_2": 14563540,
          "score_3": 11037860,
          "score_4": 20992230,
          "points_1": 0,
          "points_2": 2.5,
          "points_3": 0,
          "points_4": 2.5,
          "score_13": 24309520,
          "score_24": 35555770,
          "points_13": 0,
          "points_24": 5,
          "away_points": 5,
          "home_points": 0
        }
      ],
      "done": true,
      "left_confirmed": {
        "by": "Kevin Coffey",
        "at": 1712641838345
      },
      "right_confirmed": {
        "by": "Emily Young",
        "at": 1712641841016
      }
    }
  ],
  "players": []
}